pyprof2calltree.py
pyprof2calltree-1.4.4.dist-info/LICENSE.txt
pyprof2calltree-1.4.4.dist-info/METADATA
pyprof2calltree-1.4.4.dist-info/RECORD
pyprof2calltree-1.4.4.dist-info/WHEEL
pyprof2calltree-1.4.4.dist-info/entry_points.txt
pyprof2calltree-1.4.4.dist-info/top_level.txt
pyprof2calltree-1.4.4.dist-info/zip-safe
